distil_llm/__init__.py
distil_llm-0.0.1.dist-info/LICENSE
distil_llm-0.0.1.dist-info/WHEEL
distil_llm-0.0.1.dist-info/METADATA
distil_llm-0.0.1.dist-info/RECORD
