Metadata-Version: 2.1
Name: distil-llm
Version: 0.0.1
Summary: 
Author: davidberenstein1957
Author-email: david.m.berenstein@gmail.com
Requires-Python: >=3.8,<4.0
Classifier: Programming Language :: Python :: 3
Classifier: Programming Language :: Python :: 3.8
Classifier: Programming Language :: Python :: 3.9
Classifier: Programming Language :: Python :: 3.10
Requires-Dist: datasets (>=2.14.5,<3.0.0)
Requires-Dist: llama-cpp-python (>=0.2.11,<0.3.0)
Requires-Dist: transformers (>=4.34.1,<5.0.0)
